pandasheets/__init__.py
pandasheets/pandasheets.py
pandasheets-0.3.2.dist-info/licenses/LICENSE.txt
pandasheets-0.3.2.dist-info/METADATA
pandasheets-0.3.2.dist-info/WHEEL
pandasheets-0.3.2.dist-info/top_level.txt
pandasheets-0.3.2.dist-info/RECORD
