Metadata-Version: 2.4
Name: pandasheets
Version: 0.3.2
Summary: Lightweight wrapper around gspread that simplifies tasks like downloading, uploading, and appending data from Google Sheets using Pandas.
Author-email: Diego Magela <diego.magela1@gmail.com>
Maintainer-email: Diego Magela <diego.magela1@gmail.com>
License:                     GNU GENERAL PUBLIC LICENSE
Project-URL: Homepage, https://github.com/diegomagela/pandasheets
Keywords: Google Sheets,API
Requires-Python: >=3.8
License-File: LICENSE.txt
Requires-Dist: gspread
Requires-Dist: pandas
Dynamic: license-file
